pytest_mpl/__init__.py
pytest_mpl/plugin.py
pytest_mpl/summary/__init__.py
pytest_mpl/summary/html.py
pytest_mpl/summary/templates/base.html
pytest_mpl/summary/templates/basic.html
pytest_mpl/summary/templates/extra.js
pytest_mpl/summary/templates/filter.html
pytest_mpl/summary/templates/hash.svg
pytest_mpl/summary/templates/image.svg
pytest_mpl/summary/templates/navbar.html
pytest_mpl/summary/templates/result.html
pytest_mpl/summary/templates/result_images.html
pytest_mpl/summary/templates/styles.css
pytest_mpl-0.17.0.dist-info/LICENSE
pytest_mpl-0.17.0.dist-info/METADATA
pytest_mpl-0.17.0.dist-info/WHEEL
pytest_mpl-0.17.0.dist-info/entry_points.txt
pytest_mpl-0.17.0.dist-info/top_level.txt
pytest_mpl-0.17.0.dist-info/zip-safe
pytest_mpl-0.17.0.dist-info/RECORD
