Metadata-Version: 2.1
Name: pytest-mpl
Version: 0.17.0
Summary: pytest plugin to help with testing figures output from Matplotlib
Home-page: https://github.com/matplotlib/pytest-mpl
Author: Thomas Robitaille
Author-email: thomas.robitaille@gmail.com
License: BSD
Classifier: Development Status :: 4 - Beta
Classifier: Framework :: Pytest
Classifier: Intended Audience :: Developers
Classifier: Topic :: Software Development :: Testing
Classifier: Topic :: Scientific/Engineering :: Visualization
Classifier: Programming Language :: Python
Classifier: Programming Language :: Python :: 3
Classifier: Operating System :: OS Independent
Classifier: License :: OSI Approved :: BSD License
Requires-Python: >=3.6
License-File: LICENSE
Requires-Dist: pytest
Requires-Dist: matplotlib
Requires-Dist: packaging
Requires-Dist: Jinja2
Requires-Dist: Pillow
Requires-Dist: importlib-resources ; python_version < "3.8"
Provides-Extra: docs
Requires-Dist: sphinx ; extra == 'docs'
Requires-Dist: mpl-sphinx-theme >=3.6.0.dev0 ; extra == 'docs'
Requires-Dist: sphinx-design ; extra == 'docs'
Requires-Dist: matplotlib ==3.6 ; extra == 'docs'
Provides-Extra: test
Requires-Dist: pytest-cov ; extra == 'test'
